aurelio_sdk/__init__.py
aurelio_sdk/client.py
aurelio_sdk/client_async.py
aurelio_sdk/const.py
aurelio_sdk/exceptions.py
aurelio_sdk/logger/__init__.py
aurelio_sdk/schema.py
aurelio_sdk-0.0.17.dist-info/LICENSE
aurelio_sdk-0.0.17.dist-info/METADATA
aurelio_sdk-0.0.17.dist-info/WHEEL
aurelio_sdk-0.0.17.dist-info/RECORD
