Metadata-Version: 2.1
Name: aurelio-sdk
Version: 0.0.17
Summary: Aurelio Platform SDK
Author: Team
Author-email: hello@aurelio.ai
Requires-Python: >=3.9,<4.0
Classifier: Programming Language :: Python :: 3
Classifier: Programming Language :: Python :: 3.9
Classifier: Programming Language :: Python :: 3.10
Classifier: Programming Language :: Python :: 3.11
Requires-Dist: aiofiles (>=24.1.0,<25.0.0)
Requires-Dist: aiohttp (>=3.10.5,<4.0.0)
Requires-Dist: colorlog (>=6.8.2,<7.0.0)
Requires-Dist: pydantic (>=2.9.2,<3.0.0)
Requires-Dist: python-dotenv (>=1.0.1,<2.0.0)
Requires-Dist: requests (>=2.32.3,<3.0.0)
Requires-Dist: requests-toolbelt (>=1.0.0,<2.0.0)
